cedargrove_nau7802.py
cedargrove_nau7802-2.1.3.dist-info/licenses/LICENSE
cedargrove_nau7802-2.1.3.dist-info/METADATA
cedargrove_nau7802-2.1.3.dist-info/WHEEL
cedargrove_nau7802-2.1.3.dist-info/top_level.txt
cedargrove_nau7802-2.1.3.dist-info/RECORD
